alignak_checks_alignak/__init__.py
alignak_checks_alignak-1.1.0.data/data/share/alignak/etc/arbiter/packs/alignak/commands.cfg
alignak_checks_alignak-1.1.0.data/data/share/alignak/etc/arbiter/packs/alignak/groups.cfg
alignak_checks_alignak-1.1.0.data/data/share/alignak/etc/arbiter/packs/alignak/templates.cfg
alignak_checks_alignak-1.1.0.data/data/share/alignak/etc/backend-json/alignak/commands.json
alignak_checks_alignak-1.1.0.data/data/share/alignak/etc/backend-json/alignak/hostgroups.json
alignak_checks_alignak-1.1.0.data/data/share/alignak/etc/backend-json/alignak/hosts-templates.json
alignak_checks_alignak-1.1.0.data/data/share/alignak/etc/backend-json/alignak/servicegroups.json
alignak_checks_alignak-1.1.0.data/data/share/alignak/etc/backend-json/alignak/services-templates.json
alignak_checks_alignak-1.1.0.data/data/share/alignak/etc/backend-json/alignak/setup.sh
alignak_checks_alignak-1.1.0.data/data/share/alignak/libexec/check_alignak_arbiter.py
alignak_checks_alignak-1.1.0.data/data/share/alignak/libexec/check_alignak_daemon.py
alignak_checks_alignak-1.1.0.dist-info/LICENSE
alignak_checks_alignak-1.1.0.dist-info/METADATA
alignak_checks_alignak-1.1.0.dist-info/WHEEL
alignak_checks_alignak-1.1.0.dist-info/top_level.txt
alignak_checks_alignak-1.1.0.dist-info/RECORD
